.DS_Store
MacGyverProject-1.0.0.data/scripts/MacGyverGame.py
MacGyverProject-1.0.0.data/scripts/MacGyverMain.py
MacGyverProject-1.0.0.dist-info/DESCRIPTION.rst
MacGyverProject-1.0.0.dist-info/METADATA
MacGyverProject-1.0.0.dist-info/RECORD
MacGyverProject-1.0.0.dist-info/WHEEL
MacGyverProject-1.0.0.dist-info/metadata.json
MacGyverProject-1.0.0.dist-info/top_level.txt
content/__init__.py
content/sprite/__init__.py
content/sprite/background.gif
content/sprite/bottomLeftCorner.gif
content/sprite/bottomRightCorner.gif
content/sprite/bottomWall.gif
content/sprite/centralWallSection.gif
content/sprite/ether_beaker.gif
content/sprite/ground.gif
content/sprite/horizontalWallSection.gif
content/sprite/leftWall.gif
content/sprite/mcGyver.gif
content/sprite/mcgyverwin.gif
content/sprite/murdoc.gif
content/sprite/murdocwin.gif
content/sprite/needle.gif
content/sprite/rightWall.gif
content/sprite/syringe.gif
content/sprite/topLeftCorner.gif
content/sprite/topRightCorner.gif
content/sprite/topWall.gif
content/sprite/verticalWallSection.gif
content/structure/__init__.py
content/structure/mcgyvergame_structure.json
