Metadata-Version: 2.0
Name: MacGyverProject
Version: 1.0.0
Summary: A MacGyver based game
Home-page: https://github.com/nifred/MacGyverProject
Author: Frederic Vidry
Author-email: fred.vidry@gmail.com
License: MIT
Keywords: OpenClassrooms,Projet 3,Développeur . se d'application - Python
Platform: UNKNOWN
Classifier: Development Status :: 4 - Beta
Classifier: Intended Audience :: Education
Classifier: Topic :: Games/Entertainment :: Puzzle Games
Classifier: License :: OSI Approved :: MIT License
Classifier: Programming Language :: Python :: 3.4
Classifier: Programming Language :: Python :: 3.5
Classifier: Programming Language :: Python :: 3.6
Requires-Python: ~=3.4
Requires-Dist: pillow
